{
    "images": [{
        "name": "facial-tissue.png",
        "url": "facial-tissue.png",
        "uuid": "E13E58DE-6DCD-3B17-BF95-3EC22D484E7C"
    }],
    "object": {
        "matrix": [1,0,0,0,0,1,0,0,0,0,1,0,0,0,0,1],
        "type": "Scene",
        "uuid": "EAFFF7DB-4982-44C8-9383-AEC992D69B16",
        "children": [{
            "name": "Box",
            "uuid": "DDA9AE26-14F9-3E6A-9BDD-AF02F6D2F286",
            "matrix": [-1,0,0,0,0,0,1,0,0,1,0,0,0,0,0,1],
            "visible": true,
            "type": "Mesh",
            "material": "DDA9AE26-14F9-3E6A-9BDD-AF02F6D2F286",
            "castShadow": true,
            "receiveShadow": true,
            "geometry": "3660B608-A213-3B78-8DF4-A184A8903FD7"
        },{
            "name": "\u30b0\u30ea\u30c3\u30c9",
            "uuid": "66C5F584-56AF-3BC3-8073-CF7C84C39513",
            "matrix": [0,-1,0,0,0,0,1,0,-1,-0,0,0,0,0.13,0,1],
            "visible": true,
            "type": "Mesh",
            "castShadow": false,
            "receiveShadow": false,
            "geometry": "CEA58B5E-B7D4-30B4-96E3-4C1748B5FD2C"
        }]
    },
    "geometries": [{
        "data": {
            "uvs": [[0.161832,0.0001,0.838167,0.0001,0.838167,0.161832,0.161832,0.161833,0.9999,0.161832,0.9999,0.5,0.838167,0.5,0.838167,0.661732,0.161832,0.661732,0.161832,0.5,0.0001,0.5,0.0001,0.161833,0.838167,0.9999,0.161832,0.9999]],
            "metadata": {
                "normals": 8,
                "uvs": 1,
                "version": 3,
                "generator": "io_three",
                "vertices": 8,
                "faces": 6
            },
            "normals": [-0.577349,0.577349,-0.577349,-0.577349,-0.577349,-0.577349,-0.577349,-0.577349,0.577349,-0.577349,0.577349,0.577349,0.577349,0.577349,0.577349,0.577349,0.577349,-0.577349,0.577349,-0.577349,0.577349,0.577349,-0.577349,-0.577349],
            "name": "\u7acb\u65b9\u4f53Geometry",
            "vertices": [-0.0575,-0.115,-0,-0.0575,-0.115,0.055,-0.0575,0.115,-0,-0.0575,0.115,0.055,0.0575,-0.115,-0,0.0575,-0.115,0.055,0.0575,0.115,-0,0.0575,0.115,0.055],
            "faces": [41,2,0,1,3,2,3,0,1,0,1,2,3,41,3,7,6,2,4,5,6,2,3,4,5,0,41,7,5,4,6,7,8,9,6,4,6,7,5,41,0,4,5,1,3,9,10,11,1,7,6,2,41,0,2,6,4,3,2,6,9,1,0,5,7,41,5,7,3,1,8,7,12,13,6,4,3,2]
        },
        "type": "Geometry",
        "uuid": "3660B608-A213-3B78-8DF4-A184A8903FD7"
    },{
        "data": {
            "uvs": [],
            "metadata": {
                "normals": 9,
                "uvs": 0,
                "version": 3,
                "generator": "io_three",
                "vertices": 20,
                "faces": 9
            },
            "normals": [0,0.208533,0.977996,0,0,1,0,-0.040559,0.999176,0,0,0.999969,0,0.090487,0.99588,0,-0.257607,0.966247,0,0.031281,0.999481,0,0.075991,0.997101,0,-0.121097,0.992615],
            "name": "\u30b0\u30ea\u30c3\u30c9Geometry",
            "vertices": [0.04,-0.08,0,0.08,-0.08,0,0.04,-0.062222,-0.003791,0.08,-0.062222,-0.003791,0.04,-0.044444,0,0.08,-0.044444,0,0.04,-0.026667,-0.002304,0.08,-0.026667,-0.002304,0.04,-0.008889,0,0.08,-0.008889,0,0.04,0.008889,-0.005698,0.08,0.008889,-0.005698,0.04,0.026667,0,0.08,0.026667,0,0.04,0.044444,0.003807,0.08,0.044444,0.003807,0.04,0.062222,-0.001182,0.08,0.062222,-0.001182,0.04,0.08,0.000987,0.08,0.08,0.000987],
            "faces": [33,0,1,3,2,0,0,1,1,33,2,3,5,4,1,1,2,2,33,4,5,7,6,2,2,1,3,33,6,7,9,8,3,1,4,4,33,8,9,11,10,4,4,1,1,33,10,11,13,12,1,1,5,5,33,12,13,15,14,5,5,6,6,33,14,15,17,16,6,6,7,7,33,16,17,19,18,7,7,8,8]
        },
        "type": "Geometry",
        "uuid": "CEA58B5E-B7D4-30B4-96E3-4C1748B5FD2C"
    }],
    "textures": [{
        "mapping": 300,
        "image": "E13E58DE-6DCD-3B17-BF95-3EC22D484E7C",
        "repeat": [1,1],
        "name": "\u30c6\u30af\u30b9\u30c1\u30e3",
        "wrap": [1000,1000],
        "minFilter": 1008,
        "anisotropy": 1,
        "uuid": "43DB543A-574B-3DF7-A5AD-17757E7D783F",
        "magFilter": 1006
    }],
    "materials": [{
        "map": "43DB543A-574B-3DF7-A5AD-17757E7D783F",
        "emissive": 0,
        "shininess": 50,
        "ambient": 10724259,
        "name": "Box",
        "vertexColors": false,
        "uuid": "DDA9AE26-14F9-3E6A-9BDD-AF02F6D2F286",
        "type": "MeshPhongMaterial",
        "depthTest": true,
        "blending": "NormalBlending",
        "color": 10724259,
        "depthWrite": true,
        "specular": 8355711
    }],
    "metadata": {
        "version": 4.3,
        "generator": "io_three",
        "type": "Object",
        "sourceFile": "facial-tissue.blend"
    }
}